BIP32.txt
CHANGES
COMMAND-LINE-TOOLS.md
CREDITS
LICENSE
MANIFEST.in
README.md
TESTING.txt
pip-req.txt
setup.py
pycoin/__init__.py
pycoin/block.py
pycoin/bloomfilter.py
pycoin/encoding.py
pycoin/intbytes.py
pycoin/merkle.py
pycoin/ui.py
pycoin/version.py
pycoin/blockchain/BlockChain.py
pycoin/blockchain/ChainFinder.py
pycoin/blockchain/__init__.py
pycoin/cmds/__init__.py
pycoin/cmds/block.py
pycoin/cmds/ku.py
pycoin/cmds/msg.py
pycoin/cmds/tx.py
pycoin/coins/__init__.py
pycoin/contrib/__init__.py
pycoin/contrib/msg_signing.py
pycoin/contrib/segwit_addr.py
pycoin/contrib/who_signed.py
pycoin/convention/__init__.py
pycoin/convention/tx_fee.py
pycoin/ecdsa/__init__.py
pycoin/ecdsa/ecdsa.py
pycoin/ecdsa/ellipticcurve.py
pycoin/ecdsa/intstream.py
pycoin/ecdsa/numbertheory.py
pycoin/ecdsa/rfc6979.py
pycoin/ecdsa/secp256k1.py
pycoin/ecdsa/native/__init__.py
pycoin/ecdsa/native/bignum.py
pycoin/ecdsa/native/library.py
pycoin/key/BIP32Node.py
pycoin/key/Key.py
pycoin/key/__init__.py
pycoin/key/bip32.py
pycoin/key/electrum.py
pycoin/key/key_from_text.py
pycoin/key/validate.py
pycoin/message/InvItem.py
pycoin/message/PeerAddress.py
pycoin/message/__init__.py
pycoin/message/make_parser_and_packer.py
pycoin/networks/__init__.py
pycoin/networks/all.py
pycoin/networks/default.py
pycoin/networks/legacy_networks.py
pycoin/networks/network.py
pycoin/networks/registry.py
pycoin/serialize/__init__.py
pycoin/serialize/bitcoin_streamer.py
pycoin/serialize/streamer.py
pycoin/services/__init__.py
pycoin/services/agent.py
pycoin/services/bitcoind.py
pycoin/services/blockchain_info.py
pycoin/services/blockcypher.py
pycoin/services/blockexplorer.py
pycoin/services/chain_so.py
pycoin/services/env.py
pycoin/services/insight.py
pycoin/services/providers.py
pycoin/services/tx_db.py
pycoin/tx/Spendable.py
pycoin/tx/Tx.py
pycoin/tx/TxIn.py
pycoin/tx/TxOut.py
pycoin/tx/__init__.py
pycoin/tx/exceptions.py
pycoin/tx/tx_utils.py
pycoin/tx/pay_to/ScriptMultisig.py
pycoin/tx/pay_to/ScriptNulldata.py
strakspycoin.egg-info/PKG-INFO
strakspycoin.egg-info/SOURCES.txt
strakspycoin.egg-info/dependency_links.txt
strakspycoin.egg-info/entry_points.txt
strakspycoin.egg-info/top_level.txt